Workbook

Sheet Home
A2: Balance Sheet Builder (AS) - Lite version
B5: =HYPERLINK("#'BD'!A1", "BD - Basic Details") | D5: =HYPERLINK("#'N1'!A1", "N1 - Accounting Policies") | F5: Balance Sheet | G5: Cash Flow | H5: Notes Count
F6: =IF(Validation!D7="PASS", "RECONCILED", "UNRECONCILED") | G6: =IF(Validation!D8="PASS", "RECONCILED", "UNRECONCILED") | H6: 11 Active
B7: =HYPERLINK("#'TB'!A1", "TB - Ledger Groupings") | D7: =HYPERLINK("#'N2'!A1", "N2 - Liabilities")
B9: =HYPERLINK("#'AE'!A1", "AE - Adjustment Entries") | D9: =HYPERLINK("#'N3'!A1", "N3 - Fixed Assets") | F9: Financial Year | G9: Revenue | H9: Profit (Loss)
F10: ='BD'!B5 | G10: =IFERROR(VLOOKUP("3", 'PL'!$A:$D, 3, FALSE), 0) | H10: =IFERROR(VLOOKUP("3", 'PL'!$A:$D, 3, FALSE), 0) - IFERROR(VLOOKUP("4", 'PL'!$A:$D, 3, FALSE), 0)
B11: =HYPERLINK("#'BS'!A1", "BS - Balance Sheet") | D11: =HYPERLINK("#'N4'!A1", "N4 - Assets")
B13: =HYPERLINK("#'PL'!A1", "PL - Profit & Loss") | D13: =HYPERLINK("#'N5'!A1", "N5 - Income & Expense") | F13: VBA Control Panel | G13: Rounding Scale
G14: ='BD'!B7
B15: =HYPERLINK("#'CF'!A1", "CF - Cash Flow") | D15: =HYPERLINK("#'N6'!A1", "N6 - Other Notes")
B17: =HYPERLINK("#'TX'!A1", "TX - Tax Export")
B25: Tally Integration & Import Help Guide
B26: Step 1: Export TB from Tally | D26: In Tally Prime or Tally ERP 9, navigate to 'Display More Reports' -> 'Trial Balance'.
B27: Step 2: Excel Format | D27: Press Alt+E (Export) -> select format 'Excel (Spreadsheet)'. Ensure Ledger Name, Debit, and Credit columns are visible.
B28: Step 3: Run Macro Import | D28: In this workbook's Home dashboard, click 'Import Trial Balance' and select the exported Tally file.
B29: Step 4: Map New Accounts | D29: Go to the 'TB' sheet. Select Type, Primary Group, and Secondary Group dropdowns. The Node Code resolves automatically.
B30: Step 5: View Statements | D30: Once mapped, all statements (Balance Sheet, P&L, Cash Flow, and Notes) will automatically populate and reconcile.

Sheet BD
A1: =HYPERLINK("#Home!A1", "<- Go to Dashboard")
A3: Parameter | B3: Setting Value
A4: Company Name | B4: Mock Enterprise Ltd.
A5: Financial Year | B5: FY 2025-26
A6: Reporting Currency | B6: INR
A7: Rounding Type | B7: Unrounded
A8: Scale Factor | B8: =IF(B7="Thousands", 1000, IF(B7="Lakhs", 100000, IF(B7="Crores", 10000000, 1)))
A9: Entity Type | B9: Corporate (Schedule III)

Sheet TB
A1: =HYPERLINK("#Home!A1", "<- Go to Dashboard")
A2: Ledger Groupings
C4: 31 March 2023 | F4: 31 March 2024 | I4: 31 March 2025 | L4: Groupings
A5: GL Code | B5: GL Name | C5: Books | D5: Adjustments | E5: Final | F5: Books | G5: Adjustments | H5: Final | I5: Books | J5: Adjustments | K5: Final | L5: Type | M5: Primary Group | N5: Secondary Group | O5: Link
A6: 1001 | B6: Equity Share Capital | C6: 0 | D6: 0 | E6: =C6+D6 | F6: -250000 | G6: 0 | H6: =F6+G6 | I6: -500000 | J6: =SUMIFS('AE'!$C$6:$C$55, 'AE'!$A$6:$A$55, A6) - SUMIFS('AE'!$D$6:$D$55, 'AE'!$A$6:$A$55, A6) | K6: =I6+J6 | L6: Equity | M6: Shareholders' Funds | N6: Share Capital | O6: =IFERROR(INDEX('Chart of Accounts'!$A$4:$A$100, MATCH(N6, 'Chart of Accounts'!$B$4:$B$100, 0)), "")
A7: 1002 | B7: Retained Earnings | C7: 0 | D7: 0 | E7: =C7+D7 | F7: 0 | G7: 0 | H7: =F7+G7 | I7: -107500 | J7: =SUMIFS('AE'!$C$6:$C$55, 'AE'!$A$6:$A$55, A7) - SUMIFS('AE'!$D$6:$D$55, 'AE'!$A$6:$A$55, A7) | K7: =I7+J7 | L7: Equity | M7: Shareholders' Funds | N7: Reserves and Surplus | O7: =IFERROR(INDEX('Chart of Accounts'!$A$4:$A$100, MATCH(N7, 'Chart of Accounts'!$B$4:$B$100, 0)), "")
A8: 2001 | B8: Bank Term Loan | C8: 0 | D8: 0 | E8: =C8+D8 | F8: -100000 | G8: 0 | H8: =F8+G8 | I8: -200000 | J8: =SUMIFS('AE'!$C$6:$C$55, 'AE'!$A$6:$A$55, A8) - SUMIFS('AE'!$D$6:$D$55, 'AE'!$A$6:$A$55, A8) | K8: =I8+J8 | L8: Liability | M8: Non-Current Liabilities | N8: Long-term borrowings | O8: =IFERROR(INDEX('Chart of Accounts'!$A$4:$A$100, MATCH(N8, 'Chart of Accounts'!$B$4:$B$100, 0)), "")
A9: 3001 | B9: Trade Creditors | C9: 0 | D9: 0 | E9: =C9+D9 | F9: -40000 | G9: 0 | H9: =F9+G9 | I9: -80000 | J9: =SUMIFS('AE'!$C$6:$C$55, 'AE'!$A$6:$A$55, A9) - SUMIFS('AE'!$D$6:$D$55, 'AE'!$A$6:$A$55, A9) | K9: =I9+J9 | L9: Liability | M9: Current Liabilities | N9: Trade payables | O9: =IFERROR(INDEX('Chart of Accounts'!$A$4:$A$100, MATCH(N9, 'Chart of Accounts'!$B$4:$B$100, 0)), "")
A10: 4001 | B10: Plant and Machinery | C10: 0 | D10: 0 | E10: =C10+D10 | F10: 200000 | G10: 0 | H10: =F10+G10 | I10: 400000 | J10: =SUMIFS('AE'!$C$6:$C$55, 'AE'!$A$6:$A$55, A10) - SUMIFS('AE'!$D$6:$D$55, 'AE'!$A$6:$A$55, A10) | K10: =I10+J10 | L10: Asset | M10: Non-Current Assets | N10: Property, Plant and Equipment | O10: =IFERROR(INDEX('Chart of Accounts'!$A$4:$A$100, MATCH(N10, 'Chart of Accounts'!$B$4:$B$100, 0)), "")
A11: 5001 | B11: HDFC Bank A/c | C11: 0 | D11: 0 | E11: =C11+D11 | F11: 227500 | G11: 0 | H11: =F11+G11 | I11: 562500 | J11: =SUMIFS('AE'!$C$6:$C$55, 'AE'!$A$6:$A$55, A11) - SUMIFS('AE'!$D$6:$D$55, 'AE'!$A$6:$A$55, A11) | K11: =I11+J11 | L11: Asset | M11: Current Assets | N11: Cash and cash equivalents | O11: =IFERROR(INDEX('Chart of Accounts'!$A$4:$A$100, MATCH(N11, 'Chart of Accounts'!$B$4:$B$100, 0)), "")
A12: 5002 | B12: Accounts Receivable | C12: 0 | D12: 0 | E12: =C12+D12 | F12: 30000 | G12: 0 | H12: =F12+G12 | I12: 60000 | J12: =SUMIFS('AE'!$C$6:$C$55, 'AE'!$A$6:$A$55, A12) - SUMIFS('AE'!$D$6:$D$55, 'AE'!$A$6:$A$55, A12) | K12: =I12+J12 | L12: Asset | M12: Current Assets | N12: Trade receivables | O12: =IFERROR(INDEX('Chart of Accounts'!$A$4:$A$100, MATCH(N12, 'Chart of Accounts'!$B$4:$B$100, 0)), "")
A13: 5003 | B13: Inventory | C13: 0 | D13: 0 | E13: =C13+D13 | F13: 40000 | G13: 0 | H13: =F13+G13 | I13: 80000 | J13: =SUMIFS('AE'!$C$6:$C$55, 'AE'!$A$6:$A$55, A13) - SUMIFS('AE'!$D$6:$D$55, 'AE'!$A$6:$A$55, A13) | K13: =I13+J13 | L13: Asset | M13: Current Assets | N13: Inventories | O13: =IFERROR(INDEX('Chart of Accounts'!$A$4:$A$100, MATCH(N13, 'Chart of Accounts'!$B$4:$B$100, 0)), "")
A14: 6001 | B14: Sales Revenue | C14: 0 | D14: 0 | E14: =C14+D14 | F14: -200000 | G14: 0 | H14: =F14+G14 | I14: -400000 | J14: =SUMIFS('AE'!$C$6:$C$55, 'AE'!$A$6:$A$55, A14) - SUMIFS('AE'!$D$6:$D$55, 'AE'!$A$6:$A$55, A14) | K14: =I14+J14 | L14: Income | M14: INCOME | N14: Revenue from operations | O14: =IFERROR(INDEX('Chart of Accounts'!$A$4:$A$100, MATCH(N14, 'Chart of Accounts'!$B$4:$B$100, 0)), "")
A15: 7001 | B15: Employee Salaries | C15: 0 | D15: 0 | E15: =C15+D15 | F15: 75000 | G15: 0 | H15: =F15+G15 | I15: 150000 | J15: =SUMIFS('AE'!$C$6:$C$55, 'AE'!$A$6:$A$55, A15) - SUMIFS('AE'!$D$6:$D$55, 'AE'!$A$6:$A$55, A15) | K15: =I15+J15 | L15: Expense | M15: EXPENSES | N15: Employee benefits expense | O15: =IFERROR(INDEX('Chart of Accounts'!$A$4:$A$100, MATCH(N15, 'Chart of Accounts'!$B$4:$B$100, 0)), "")
A16: 7002 | B16: Interest Expense | C16: 0 | D16: 0 | E16: =C16+D16 | F16: 7500 | G16: 0 | H16: =F16+G16 | I16: 15000 | J16: =SUMIFS('AE'!$C$6:$C$55, 'AE'!$A$6:$A$55, A16) - SUMIFS('AE'!$D$6:$D$55, 'AE'!$A$6:$A$55, A16) | K16: =I16+J16 | L16: Expense | M16: EXPENSES | N16: Finance costs | O16: =IFERROR(INDEX('Chart of Accounts'!$A$4:$A$100, MATCH(N16, 'Chart of Accounts'!$B$4:$B$100, 0)), "")
A17: 7004 | B17: Office Rent | C17: 0 | D17: 0 | E17: =C17+D17 | F17: 10000 | G17: 0 | H17: =F17+G17 | I17: 20000 | J17: =SUMIFS('AE'!$C$6:$C$55, 'AE'!$A$6:$A$55, A17) - SUMIFS('AE'!$D$6:$D$55, 'AE'!$A$6:$A$55, A17) | K17: =I17+J17 | L17: Expense | M17: EXPENSES | N17: Other expenses | O17: =IFERROR(INDEX('Chart of Accounts'!$A$4:$A$100, MATCH(N17, 'Chart of Accounts'!$B$4:$B$100, 0)), "")
A18: Total | C18: =SUM(C6:C17) | D18: =SUM(D6:D17) | E18: =SUM(E6:E17) | F18: =SUM(F6:F17) | G18: =SUM(G6:G17) | H18: =SUM(H6:H17) | I18: =SUM(I6:I17) | J18: =SUM(J6:J17) | K18: =SUM(K6:K17)

Sheet AE
A1: =HYPERLINK("#Home!A1", "<- Go to Dashboard")
A3: Post Adjustment Entries
A5: GL Code | B5: GL Name | C5: Debit Amount | D5: Credit Amount | E5: Narration
B6: =IF(ISBLANK(A6), "", IFERROR(VLOOKUP(A6, 'TB'!$A:$B, 2, FALSE), "Invalid GL"))
B7: =IF(ISBLANK(A7), "", IFERROR(VLOOKUP(A7, 'TB'!$A:$B, 2, FALSE), "Invalid GL"))
B8: =IF(ISBLANK(A8), "", IFERROR(VLOOKUP(A8, 'TB'!$A:$B, 2, FALSE), "Invalid GL"))
B9: =IF(ISBLANK(A9), "", IFERROR(VLOOKUP(A9, 'TB'!$A:$B, 2, FALSE), "Invalid GL"))
B10: =IF(ISBLANK(A10), "", IFERROR(VLOOKUP(A10, 'TB'!$A:$B, 2, FALSE), "Invalid GL"))
B11: =IF(ISBLANK(A11), "", IFERROR(VLOOKUP(A11, 'TB'!$A:$B, 2, FALSE), "Invalid GL"))
B12: =IF(ISBLANK(A12), "", IFERROR(VLOOKUP(A12, 'TB'!$A:$B, 2, FALSE), "Invalid GL"))
B13: =IF(ISBLANK(A13), "", IFERROR(VLOOKUP(A13, 'TB'!$A:$B, 2, FALSE), "Invalid GL"))
B14: =IF(ISBLANK(A14), "", IFERROR(VLOOKUP(A14, 'TB'!$A:$B, 2, FALSE), "Invalid GL"))
B15: =IF(ISBLANK(A15), "", IFERROR(VLOOKUP(A15, 'TB'!$A:$B, 2, FALSE), "Invalid GL"))
B16: =IF(ISBLANK(A16), "", IFERROR(VLOOKUP(A16, 'TB'!$A:$B, 2, FALSE), "Invalid GL"))
B17: =IF(ISBLANK(A17), "", IFERROR(VLOOKUP(A17, 'TB'!$A:$B, 2, FALSE), "Invalid GL"))
... B55: =IF(ISBLANK(A55), "", IFERROR(VLOOKUP(A55, 'TB'!$A:$B, 2, FALSE), "Invalid GL"))

Sheet BS
A1: =HYPERLINK("#Home!A1", "<- Go to Dashboard")
A2: Mock Enterprise Ltd.
A3: Balance Sheet as at March 31, 2025
A5: Node Code | B5: Particulars | C5: 31 March 2025 | D5: 31 March 2024
A6: 1 | B6: =IF('BD'!$B$9="Non-Corporate", "CAPITAL AND LIABILITIES", "EQUITY AND LIABILITIES") | C6: =C7+C10+C12 | D6: =D7+D10+D12
A7: 1.1 | B7: =IF('BD'!$B$9="Non-Corporate", "Partners' / Proprietor's Funds", "Shareholders' Funds") | C7: =SUM(C8:C9) | D7: =SUM(D8:D9)
A8: 1.1.1 | B8: =IF('BD'!$B$9="Non-Corporate", "Partners' / Proprietor's Capital Account", "Share Capital") | C8: =(-SUMIFS('TB'!$K$6:$K$500, 'TB'!$O$6:$O$500, A8)) / 'BD'!$B$8 | D8: =(-SUMIFS('TB'!$H$6:$H$500, 'TB'!$O$6:$O$500, A8)) / 'BD'!$B$8
A9: 1.1.2 | B9: =IF('BD'!$B$9="Non-Corporate", "Reserves & Profit / Loss Balance", "Reserves and Surplus") | C9: =(-SUMIFS('TB'!$K$6:$K$500, 'TB'!$O$6:$O$500, A9)) / 'BD'!$B$8 + 'PL'!$C$6 - 'PL'!$C$9 | D9: =(-SUMIFS('TB'!$H$6:$H$500, 'TB'!$O$6:$O$500, A9)) / 'BD'!$B$8 + 'PL'!$D$6 - 'PL'!$D$9
A10: 1.2 | B10: Non-Current Liabilities | C10: =C11 | D10: =D11
A11: 1.2.1 | B11: Long-term borrowings | C11: =(-SUMIFS('TB'!$K$6:$K$500, 'TB'!$O$6:$O$500, A11)) / 'BD'!$B$8 | D11: =(-SUMIFS('TB'!$H$6:$H$500, 'TB'!$O$6:$O$500, A11)) / 'BD'!$B$8
A12: 1.3 | B12: Current Liabilities | C12: =SUM(C13:C16) | D12: =SUM(D13:D16)
A13: 1.3.1 | B13: Short-term borrowings | C13: =(-SUMIFS('TB'!$K$6:$K$500, 'TB'!$O$6:$O$500, A13)) / 'BD'!$B$8 | D13: =(-SUMIFS('TB'!$H$6:$H$500, 'TB'!$O$6:$O$500, A13)) / 'BD'!$B$8
A14: 1.3.2 | B14: Trade payables | C14: =(-SUMIFS('TB'!$K$6:$K$500, 'TB'!$O$6:$O$500, A14)) / 'BD'!$B$8 | D14: =(-SUMIFS('TB'!$H$6:$H$500, 'TB'!$O$6:$O$500, A14)) / 'BD'!$B$8
A15: 1.3.3 | B15: Other current liabilities | C15: =(-SUMIFS('TB'!$K$6:$K$500, 'TB'!$O$6:$O$500, A15)) / 'BD'!$B$8 | D15: =(-SUMIFS('TB'!$H$6:$H$500, 'TB'!$O$6:$O$500, A15)) / 'BD'!$B$8
A16: 1.3.4 | B16: Short-term provisions | C16: =(-SUMIFS('TB'!$K$6:$K$500, 'TB'!$O$6:$O$500, A16)) / 'BD'!$B$8 | D16: =(-SUMIFS('TB'!$H$6:$H$500, 'TB'!$O$6:$O$500, A16)) / 'BD'!$B$8
A17: 2 | B17: ASSETS | C17: =C18+C23 | D17: =D18+D23
A18: 2.1 | B18: Non-Current Assets | C18: =C19+C22 | D18: =D19+D22
A19: 2.1.1 | B19: Property, Plant and Equipment and Intangible Assets | C19: =SUM(C20:C21) | D19: =SUM(D20:D21)
A20: 2.1.1.1 | B20: Property, Plant and Equipment | C20: =(SUMIFS('TB'!$K$6:$K$500, 'TB'!$O$6:$O$500, A20)) / 'BD'!$B$8 | D20: =(SUMIFS('TB'!$H$6:$H$500, 'TB'!$O$6:$O$500, A20)) / 'BD'!$B$8
A21: 2.1.1.2 | B21: Intangible assets | C21: =(SUMIFS('TB'!$K$6:$K$500, 'TB'!$O$6:$O$500, A21)) / 'BD'!$B$8 | D21: =(SUMIFS('TB'!$H$6:$H$500, 'TB'!$O$6:$O$500, A21)) / 'BD'!$B$8
A22: 2.1.2 | B22: Non-current investments | C22: =(SUMIFS('TB'!$K$6:$K$500, 'TB'!$O$6:$O$500, A22)) / 'BD'!$B$8 | D22: =(SUMIFS('TB'!$H$6:$H$500, 'TB'!$O$6:$O$500, A22)) / 'BD'!$B$8
A23: 2.2 | B23: Current Assets | C23: =SUM(C24:C29) | D23: =SUM(D24:D29)
A24: 2.2.1 | B24: Current investments | C24: =(SUMIFS('TB'!$K$6:$K$500, 'TB'!$O$6:$O$500, A24)) / 'BD'!$B$8 | D24: =(SUMIFS('TB'!$H$6:$H$500, 'TB'!$O$6:$O$500, A24)) / 'BD'!$B$8
A25: 2.2.2 | B25: Inventories | C25: =(SUMIFS('TB'!$K$6:$K$500, 'TB'!$O$6:$O$500, A25)) / 'BD'!$B$8 | D25: =(SUMIFS('TB'!$H$6:$H$500, 'TB'!$O$6:$O$500, A25)) / 'BD'!$B$8
A26: 2.2.3 | B26: Trade receivables | C26: =(SUMIFS('TB'!$K$6:$K$500, 'TB'!$O$6:$O$500, A26)) / 'BD'!$B$8 | D26: =(SUMIFS('TB'!$H$6:$H$500, 'TB'!$O$6:$O$500, A26)) / 'BD'!$B$8
A27: 2.2.4 | B27: Cash and cash equivalents | C27: =(SUMIFS('TB'!$K$6:$K$500, 'TB'!$O$6:$O$500, A27)) / 'BD'!$B$8 | D27: =(SUMIFS('TB'!$H$6:$H$500, 'TB'!$O$6:$O$500, A27)) / 'BD'!$B$8
A28: 2.2.5 | B28: Short-term loans and advances | C28: =(SUMIFS('TB'!$K$6:$K$500, 'TB'!$O$6:$O$500, A28)) / 'BD'!$B$8 | D28: =(SUMIFS('TB'!$H$6:$H$500, 'TB'!$O$6:$O$500, A28)) / 'BD'!$B$8
A29: 2.2.6 | B29: Other current assets | C29: =(SUMIFS('TB'!$K$6:$K$500, 'TB'!$O$6:$O$500, A29)) / 'BD'!$B$8 | D29: =(SUMIFS('TB'!$H$6:$H$500, 'TB'!$O$6:$O$500, A29)) / 'BD'!$B$8

Sheet PL
A1: =HYPERLINK("#Home!A1", "<- Go to Dashboard")
A2: Mock Enterprise Ltd.
A3: Profit & Loss for the year ended March 31, 2025
A5: Node Code | B5: Particulars | C5: 31 March 2025 | D5: 31 March 2024
A6: 3 | B6: INCOME | C6: =SUM(C7:C8) | D6: =SUM(D7:D8)
A7: 3.1 | B7: Revenue from operations | C7: =(-SUMIFS('TB'!$K$6:$K$500, 'TB'!$O$6:$O$500, A7)) / 'BD'!$B$8 | D7: =(-SUMIFS('TB'!$H$6:$H$500, 'TB'!$O$6:$O$500, A7)) / 'BD'!$B$8
A8: 3.2 | B8: Other income | C8: =(-SUMIFS('TB'!$K$6:$K$500, 'TB'!$O$6:$O$500, A8)) / 'BD'!$B$8 | D8: =(-SUMIFS('TB'!$H$6:$H$500, 'TB'!$O$6:$O$500, A8)) / 'BD'!$B$8
A9: 4 | B9: EXPENSES | C9: =SUM(C10:C15) | D9: =SUM(D10:D15)
A10: 4.1 | B10: Cost of materials consumed | C10: =(SUMIFS('TB'!$K$6:$K$500, 'TB'!$O$6:$O$500, A10)) / 'BD'!$B$8 | D10: =(SUMIFS('TB'!$H$6:$H$500, 'TB'!$O$6:$O$500, A10)) / 'BD'!$B$8
A11: 4.2 | B11: Purchase of Stock-in-Trade | C11: =(SUMIFS('TB'!$K$6:$K$500, 'TB'!$O$6:$O$500, A11)) / 'BD'!$B$8 | D11: =(SUMIFS('TB'!$H$6:$H$500, 'TB'!$O$6:$O$500, A11)) / 'BD'!$B$8
A12: 4.3 | B12: Employee benefits expense | C12: =(SUMIFS('TB'!$K$6:$K$500, 'TB'!$O$6:$O$500, A12)) / 'BD'!$B$8 | D12: =(SUMIFS('TB'!$H$6:$H$500, 'TB'!$O$6:$O$500, A12)) / 'BD'!$B$8
A13: 4.4 | B13: Finance costs | C13: =(SUMIFS('TB'!$K$6:$K$500, 'TB'!$O$6:$O$500, A13)) / 'BD'!$B$8 | D13: =(SUMIFS('TB'!$H$6:$H$500, 'TB'!$O$6:$O$500, A13)) / 'BD'!$B$8
A14: 4.5 | B14: Depreciation and amortization expense | C14: =(SUMIFS('TB'!$K$6:$K$500, 'TB'!$O$6:$O$500, A14)) / 'BD'!$B$8 | D14: =(SUMIFS('TB'!$H$6:$H$500, 'TB'!$O$6:$O$500, A14)) / 'BD'!$B$8
A15: 4.6 | B15: Other expenses | C15: =(SUMIFS('TB'!$K$6:$K$500, 'TB'!$O$6:$O$500, A15)) / 'BD'!$B$8 | D15: =(SUMIFS('TB'!$H$6:$H$500, 'TB'!$O$6:$O$500, A15)) / 'BD'!$B$8

Sheet CF
A1: =HYPERLINK("#Home!A1", "<- Go to Dashboard")
A2: Indirect Cash Flow Statement
A4: Particulars | B4: Amount
A5: Cash Flow from Operating Activities
A6: Net Profit Before Tax | B6: =IFERROR(VLOOKUP("3", 'PL'!$A:$D, 3, FALSE), 0) - IFERROR(VLOOKUP("4", 'PL'!$A:$D, 3, FALSE), 0)
A7: Adjustment: Depreciation and Amortization | B7: =IFERROR(VLOOKUP("4.5", 'PL'!$A:$D, 3, FALSE), 0)
A8: Operating Profit before Working Capital Changes | B8: =SUM(B6:B7)
A9: Changes in Trade Payables | B9: =IFERROR(VLOOKUP("1.3.2", 'BS'!$A:$D, 3, FALSE), 0) - IFERROR(VLOOKUP("1.3.2", 'BS'!$A:$D, 4, FALSE), 0)
A10: Changes in Trade Receivables | B10: =-(IFERROR(VLOOKUP("2.2.3", 'BS'!$A:$D, 3, FALSE), 0) - IFERROR(VLOOKUP("2.2.3", 'BS'!$A:$D, 4, FALSE), 0))
A11: Changes in Inventories | B11: =-(IFERROR(VLOOKUP("2.2.2", 'BS'!$A:$D, 3, FALSE), 0) - IFERROR(VLOOKUP("2.2.2", 'BS'!$A:$D, 4, FALSE), 0))
A12: Net Cash from Operating Activities | B12: =B8+B9+B10+B11
A13: Cash Flow from Investing Activities
A14: Purchase of Property, Plant and Equipment | B14: =-(IFERROR(VLOOKUP("2.1.1.1", 'BS'!$A:$D, 3, FALSE), 0) - IFERROR(VLOOKUP("2.1.1.1", 'BS'!$A:$D, 4, FALSE), 0))
A15: Net Cash from Investing Activities | B15: =B14
A16: Cash Flow from Financing Activities
A17: Proceeds from Share Capital | B17: =IFERROR(VLOOKUP("1.1.1", 'BS'!$A:$D, 3, FALSE), 0) - IFERROR(VLOOKUP("1.1.1", 'BS'!$A:$D, 4, FALSE), 0)
A18: Proceeds from Long-term Borrowings | B18: =IFERROR(VLOOKUP("1.2.1", 'BS'!$A:$D, 3, FALSE), 0) - IFERROR(VLOOKUP("1.2.1", 'BS'!$A:$D, 4, FALSE), 0)
A19: Net Cash from Financing Activities | B19: =B17+B18
A20: Net Increase / (Decrease) in Cash | B20: =B12+B15+B19
A21: Opening Cash & Cash Equivalents | B21: =IFERROR(VLOOKUP("2.2.4", 'BS'!$A:$D, 4, FALSE), 0)
A22: Closing Cash & Cash Equivalents | B22: =B20+B21

Sheet Ageing
A1: =HYPERLINK("#Home!A1", "<- Go to Dashboard")
A2: Ageing Schedules (Trade Receivables & Payables)
A4: Trade Receivables Ageing Schedule
A5: Particulars | B5: Less than 6 months | C5: 6 months - 1 year | D5: 1 - 2 years | E5: 2 - 3 years | F5: More than 3 years | G5: Total
A6: (i) Undisputed Trade Receivables - considered good | B6: 0 | C6: 0 | D6: 0 | E6: 0 | F6: 0 | G6: =SUM(B6:F6)
A7: (ii) Undisputed Trade Receivables - considered doubtful | B7: 0 | C7: 0 | D7: 0 | E7: 0 | F7: 0 | G7: =SUM(B7:F7)
A8: (iii) Disputed Trade Receivables - considered good | B8: 0 | C8: 0 | D8: 0 | E8: 0 | F8: 0 | G8: =SUM(B8:F8)
A9: (iv) Disputed Trade Receivables - considered doubtful | B9: 0 | C9: 0 | D9: 0 | E9: 0 | F9: 0 | G9: =SUM(B9:F9)
A10: Total Trade Receivables | B10: =SUM(B6:B9) | C10: =SUM(C6:C9) | D10: =SUM(D6:D9) | E10: =SUM(E6:E9) | F10: =SUM(F6:F9) | G10: =SUM(G6:G9)
A11: Balance Sheet Control Total | G11: =IFERROR(VLOOKUP("2.2.3", 'BS'!$A:$D, 3, FALSE), 0)
A12: Unreconciled Difference | G12: =G10-G11
A14: Trade Payables Ageing Schedule
A15: Particulars | B15: Less than 1 year | C15: 1 - 2 years | D15: 2 - 3 years | E15: More than 3 years | G15: Total
A16: (i) MSME | B16: 0 | C16: 0 | D16: 0 | E16: 0 | F16: - | G16: =SUM(B16:E16)
A17: (ii) Others | B17: 0 | C17: 0 | D17: 0 | E17: 0 | F17: - | G17: =SUM(B17:E17)
A18: (iii) Disputed dues - MSME | B18: 0 | C18: 0 | D18: 0 | E18: 0 | F18: - | G18: =SUM(B18:E18)
A19: (iv) Disputed dues - Others | B19: 0 | C19: 0 | D19: 0 | E19: 0 | F19: - | G19: =SUM(B19:E19)
A20: Total Trade Payables | B20: =SUM(B16:B19) | C20: =SUM(C16:C19) | D20: =SUM(D16:D19) | E20: =SUM(E16:E19) | F20: - | G20: =SUM(G16:G19)
A21: Balance Sheet Control Total | G21: =IFERROR(VLOOKUP("1.3.2", 'BS'!$A:$D, 3, FALSE), 0)
A22: Unreconciled Difference | G22: =G20-G21

Sheet N1
A1: =HYPERLINK("#Home!A1", "<- Go to Dashboard")
A3: Note 1: Significant Accounting Policies
A5: 1. Basis of Preparation:
A6: The financial statements are prepared under historical cost convention on an accrual basis of accounting in accordance with the standard Indian Accounting Standards (AS) and the provisions of the Companies Act, 2013.
A8: 2. Property, Plant and Equipment (PPE):
A9: PPE are stated at cost of acquisition less accumulated depreciation. Depreciation is calculated using the Straight Line Method (SLM) based on the useful lives of assets prescribed under Schedule II of the Companies Act, 2013.
A11: 3. Revenue Recognition:
A12: Revenue is recognized when control of the goods or services is transferred to the customer at an amount that reflects the consideration to which the company expects to be entitled.

Sheet N2
A1: =HYPERLINK("#Home!A1", "<- Go to Dashboard")
A4: Note 2: Share Capital
A5: GL Code | B5: GL Particulars | C5: Amount
A6: 1001 | B6: Equity Share Capital | C6: =IFERROR(VLOOKUP(A6, 'TB'!$A:$O, 11, FALSE), 0) / 'BD'!$B$8
B7: Total Share Capital | C7: =SUM(C6:C6)
A9: Note 3: Reserves and Surplus
A10: GL Code | B10: GL Particulars | C10: Amount
A11: 1002 | B11: Retained Earnings | C11: =IFERROR(VLOOKUP(A11, 'TB'!$A:$O, 11, FALSE), 0) / 'BD'!$B$8
B12: Total Reserves and Surplus | C12: =SUM(C11:C11)
A14: Note 4: Trade Payables
A15: GL Code | B15: GL Particulars | C15: Amount
A16: 3001 | B16: Trade Creditors | C16: =IFERROR(VLOOKUP(A16, 'TB'!$A:$O, 11, FALSE), 0) / 'BD'!$B$8
B17: Total Trade Payables | C17: =SUM(C16:C16)

Sheet N3
A1: =HYPERLINK("#Home!A1", "<- Go to Dashboard")
A4: Note 5: Property, Plant and Equipment
A5: GL Code | B5: GL Particulars | C5: Amount
A6: 4001 | B6: Plant and Machinery | C6: =IFERROR(VLOOKUP(A6, 'TB'!$A:$O, 11, FALSE), 0) / 'BD'!$B$8
B7: Total Property, Plant and Equipment | C7: =SUM(C6:C6)

Sheet N4
A1: =HYPERLINK("#Home!A1", "<- Go to Dashboard")
A4: Note 6: Trade Receivables
A5: GL Code | B5: GL Particulars | C5: Amount
A6: 5002 | B6: Accounts Receivable | C6: =IFERROR(VLOOKUP(A6, 'TB'!$A:$O, 11, FALSE), 0) / 'BD'!$B$8
B7: Total Trade Receivables | C7: =SUM(C6:C6)
A9: Note 7: Cash and Cash Equivalents
A10: GL Code | B10: GL Particulars | C10: Amount
A11: 5001 | B11: HDFC Bank A/c | C11: =IFERROR(VLOOKUP(A11, 'TB'!$A:$O, 11, FALSE), 0) / 'BD'!$B$8
B12: Total Cash and Cash Equivalents | C12: =SUM(C11:C11)

Sheet N5
A1: =HYPERLINK("#Home!A1", "<- Go to Dashboard")
A4: Note 8: Revenue from Operations
A5: GL Code | B5: GL Particulars | C5: Amount
A6: 6001 | B6: Sales Revenue | C6: =IFERROR(VLOOKUP(A6, 'TB'!$A:$O, 11, FALSE), 0) / 'BD'!$B$8
B7: Total Revenue from Operations | C7: =SUM(C6:C6)
A9: Note 9: Employee Benefit Expenses
A10: GL Code | B10: GL Particulars | C10: Amount
A11: 7001 | B11: Employee Salaries | C11: =IFERROR(VLOOKUP(A11, 'TB'!$A:$O, 11, FALSE), 0) / 'BD'!$B$8
B12: Total Employee Benefit Expenses | C12: =SUM(C11:C11)

Sheet N6
A1: =HYPERLINK("#Home!A1", "<- Go to Dashboard")
A3: Note 11: Analytical Ratios
A5: Ratio Name | B5: Formula / Details | C5: Current Value
A6: Current Ratio | B6: Current Assets / Current Liabilities | C6: =IFERROR(IFERROR(VLOOKUP("2.2", 'BS'!$A:$D, 3, FALSE), 0)/IFERROR(VLOOKUP("1.3", 'BS'!$A:$D, 3, FALSE), 1), 0)
A7: Debt to Equity Ratio | B7: Long-term Borrowings / Shareholders' Funds | C7: =IFERROR(IFERROR(VLOOKUP("1.2", 'BS'!$A:$D, 3, FALSE), 0)/IFERROR(VLOOKUP("1.1", 'BS'!$A:$D, 3, FALSE), 1), 0)

Sheet TX
A1: =HYPERLINK("#Home!A1", "<- Go to Dashboard")
A2: Income Tax Return - Balance Sheet and Profit & Loss
A3: Year ended March 31, 2025
A4: All amounts in INR Unrounded, unless otherwise stated
A5: Field Name | B5: Amount CY | C5: Amount PY
A6: Share Capital | B6: =IFERROR(VLOOKUP("1.1.1", BS!$A:$D, 3, FALSE), 0) | C6: =IFERROR(VLOOKUP("1.1.1", BS!$A:$D, 4, FALSE), 0)
A7: Reserves and Surplus | B7: =IFERROR(VLOOKUP("1.1.2", BS!$A:$D, 3, FALSE), 0) | C7: =IFERROR(VLOOKUP("1.1.2", BS!$A:$D, 4, FALSE), 0)
A8: Long-term Borrowings | B8: =IFERROR(VLOOKUP("1.2.1", BS!$A:$D, 3, FALSE), 0) | C8: =IFERROR(VLOOKUP("1.2.1", BS!$A:$D, 4, FALSE), 0)
A9: Short-term Borrowings | B9: =IFERROR(VLOOKUP("1.3.1", BS!$A:$D, 3, FALSE), 0) | C9: =IFERROR(VLOOKUP("1.3.1", BS!$A:$D, 4, FALSE), 0)
A10: Trade Payables | B10: =IFERROR(VLOOKUP("1.3.2", BS!$A:$D, 3, FALSE), 0) | C10: =IFERROR(VLOOKUP("1.3.2", BS!$A:$D, 4, FALSE), 0)
A11: Other Current Liabilities | B11: =IFERROR(VLOOKUP("1.3.3", BS!$A:$D, 3, FALSE), 0) | C11: =IFERROR(VLOOKUP("1.3.3", BS!$A:$D, 4, FALSE), 0)
A12: Short-term Provisions | B12: =IFERROR(VLOOKUP("1.3.4", BS!$A:$D, 3, FALSE), 0) | C12: =IFERROR(VLOOKUP("1.3.4", BS!$A:$D, 4, FALSE), 0)
A13: Property, Plant and Equipment | B13: =IFERROR(VLOOKUP("2.1.1.1", BS!$A:$D, 3, FALSE), 0) | C13: =IFERROR(VLOOKUP("2.1.1.1", BS!$A:$D, 4, FALSE), 0)
A14: Intangible Assets | B14: =IFERROR(VLOOKUP("2.1.1.2", BS!$A:$D, 3, FALSE), 0) | C14: =IFERROR(VLOOKUP("2.1.1.2", BS!$A:$D, 4, FALSE), 0)
A15: Non-Current Investments | B15: =IFERROR(VLOOKUP("2.1.2", BS!$A:$D, 3, FALSE), 0) | C15: =IFERROR(VLOOKUP("2.1.2", BS!$A:$D, 4, FALSE), 0)
A16: Trade Receivables | B16: =IFERROR(VLOOKUP("2.2.3", BS!$A:$D, 3, FALSE), 0) | C16: =IFERROR(VLOOKUP("2.2.3", BS!$A:$D, 4, FALSE), 0)
A17: Cash and Cash Equivalents | B17: =IFERROR(VLOOKUP("2.2.4", BS!$A:$D, 3, FALSE), 0) | C17: =IFERROR(VLOOKUP("2.2.4", BS!$A:$D, 4, FALSE), 0)
A18: Short-term Loans and Advances | B18: =IFERROR(VLOOKUP("2.2.5", BS!$A:$D, 3, FALSE), 0) | C18: =IFERROR(VLOOKUP("2.2.5", BS!$A:$D, 4, FALSE), 0)
A19: Other Current Assets | B19: =IFERROR(VLOOKUP("2.2.6", BS!$A:$D, 3, FALSE), 0) | C19: =IFERROR(VLOOKUP("2.2.6", BS!$A:$D, 4, FALSE), 0)
A20: Revenue from Operations | B20: =IFERROR(VLOOKUP("3.1", PL!$A:$D, 3, FALSE), 0) | C20: =IFERROR(VLOOKUP("3.1", PL!$A:$D, 4, FALSE), 0)
A21: Other Income | B21: =IFERROR(VLOOKUP("3.2", PL!$A:$D, 3, FALSE), 0) | C21: =IFERROR(VLOOKUP("3.2", PL!$A:$D, 4, FALSE), 0)
A22: Cost of Materials Consumed | B22: =IFERROR(VLOOKUP("4.1", PL!$A:$D, 3, FALSE), 0) | C22: =IFERROR(VLOOKUP("4.1", PL!$A:$D, 4, FALSE), 0)
A23: Purchase of Stock-in-Trade | B23: =IFERROR(VLOOKUP("4.2", PL!$A:$D, 3, FALSE), 0) | C23: =IFERROR(VLOOKUP("4.2", PL!$A:$D, 4, FALSE), 0)
A24: Employee Benefits Expense | B24: =IFERROR(VLOOKUP("4.3", PL!$A:$D, 3, FALSE), 0) | C24: =IFERROR(VLOOKUP("4.3", PL!$A:$D, 4, FALSE), 0)
A25: Finance Costs | B25: =IFERROR(VLOOKUP("4.4", PL!$A:$D, 3, FALSE), 0) | C25: =IFERROR(VLOOKUP("4.4", PL!$A:$D, 4, FALSE), 0)
A26: Depreciation and Amortization | B26: =IFERROR(VLOOKUP("4.5", PL!$A:$D, 3, FALSE), 0) | C26: =IFERROR(VLOOKUP("4.5", PL!$A:$D, 4, FALSE), 0)
A27: Other Expenses | B27: =IFERROR(VLOOKUP("4.6", PL!$A:$D, 3, FALSE), 0) | C27: =IFERROR(VLOOKUP("4.6", PL!$A:$D, 4, FALSE), 0)

Sheet Validation
A1: =HYPERLINK("#Home!A1", "<- Go to Dashboard")
A3: Diagnostic Validation Controls
A5: Diagnostic Description | B5: Actual Value 1 | C5: Actual Value 2 | D5: Status
A6: Trial Balance Debits = Credits | B6: =SUMIF('TB'!$K$6:$K$500, ">0") | C6: =-SUMIF('TB'!$K$6:$K$500, "<0") | D6: =IF(ROUND(B6-C6,2)=0, "PASS", "FAIL")
A7: Total Assets = Total Equity & Liabilities | B7: =IFERROR(VLOOKUP("2", 'BS'!$A:$D, 3, FALSE), 0) | C7: =IFERROR(VLOOKUP("1", 'BS'!$A:$D, 3, FALSE), 0) | D7: =IF(ROUND(B7-C7,2)=0, "PASS", "FAIL")
A8: Cash Flow Reconciled (Opening + Change = Closing) | B8: =IFERROR(VLOOKUP("Closing Cash & Cash Equivalents", 'CF'!$A:$B, 2, FALSE), 0) | C8: =IFERROR(VLOOKUP("2.2.4", 'BS'!$A:$D, 3, FALSE), 0) | D8: =IF(ROUND(B8-C8,2)=0, "PASS", "FAIL")

Sheet Chart of Accounts
A1: Node Code | B1: Node Name | C1: Type | D1: Statement
A2: 1 | B2: EQUITY AND LIABILITIES | C2: EQUITY | D2: BALANCE_SHEET
A3: 1.1 | B3: Shareholders' Funds | C3: EQUITY | D3: BALANCE_SHEET
A4: 1.1.1 | B4: Share Capital | C4: EQUITY | D4: BALANCE_SHEET
A5: 1.1.2 | B5: Reserves and Surplus | C5: EQUITY | D5: BALANCE_SHEET
A6: 1.2 | B6: Non-Current Liabilities | C6: LIABILITY | D6: BALANCE_SHEET
A7: 1.2.1 | B7: Long-term borrowings | C7: LIABILITY | D7: BALANCE_SHEET
A8: 1.3 | B8: Current Liabilities | C8: LIABILITY | D8: BALANCE_SHEET
A9: 1.3.1 | B9: Short-term borrowings | C9: LIABILITY | D9: BALANCE_SHEET
A10: 1.3.2 | B10: Trade payables | C10: LIABILITY | D10: BALANCE_SHEET
A11: 1.3.3 | B11: Other current liabilities | C11: LIABILITY | D11: BALANCE_SHEET
A12: 1.3.4 | B12: Short-term provisions | C12: LIABILITY | D12: BALANCE_SHEET
... A35: 4.6 | B35: Other expenses | C35: EXPENSE | D35: PROFIT_LOSS
